params/__init__.py
params/params.py
py_params-0.1.5.dist-info/LICENSE
py_params-0.1.5.dist-info/METADATA
py_params-0.1.5.dist-info/WHEEL
py_params-0.1.5.dist-info/top_level.txt
py_params-0.1.5.dist-info/RECORD
